pycompose.py
pycompose-1.2.1.dist-info/LICENSE
pycompose-1.2.1.dist-info/METADATA
pycompose-1.2.1.dist-info/WHEEL
pycompose-1.2.1.dist-info/top_level.txt
pycompose-1.2.1.dist-info/RECORD
