Metadata-Version: 2.1
Name: pycompose
Version: 1.2.1
Summary: A simple way to inject composition through inheritance syntax.
Home-page: https://github.com/timfi/pycompose
Author: Tim Fischer
Author-email: me@timfi.dev
License: MIT
Platform: UNKNOWN
Classifier: Development Status :: 4 - Beta
Classifier: Intended Audience :: Developers
Classifier: Natural Language :: English
Classifier: License :: OSI Approved :: MIT License
Classifier: Programming Language :: Python
Classifier: Programming Language :: Python :: 3
Classifier: Programming Language :: Python :: Implementation :: CPython
Classifier: Operating System :: OS Independent
Classifier: Topic :: Software Development :: Code Generators
Classifier: Typing :: Typed
